gnosis/__init__.py
gnosis/py.typed
gnosis/cowsap/__init__.py
gnosis/cowsap/cow_swap_api.py
gnosis/cowsap/order.py
gnosis/cowsap/tests/__init__.py
gnosis/cowsap/tests/test_cow_swap_api.py
gnosis/eth/__init__.py
gnosis/eth/constants.py
gnosis/eth/ethereum_client.py
gnosis/eth/ethereum_network.py
gnosis/eth/exceptions.py
gnosis/eth/multicall.py
gnosis/eth/typing.py
gnosis/eth/utils.py
gnosis/eth/account_abstraction/__init__.py
gnosis/eth/account_abstraction/bundler_client.py
gnosis/eth/account_abstraction/constants.py
gnosis/eth/account_abstraction/exceptions.py
gnosis/eth/account_abstraction/user_operation.py
gnosis/eth/account_abstraction/user_operation_receipt.py
gnosis/eth/clients/__init__.py
gnosis/eth/clients/blockscout_client.py
gnosis/eth/clients/contract_metadata.py
gnosis/eth/clients/ens_client.py
gnosis/eth/clients/etherscan_client.py
gnosis/eth/clients/sourcify_client.py
gnosis/eth/contracts/__init__.py
gnosis/eth/contracts/contract_base.py
gnosis/eth/contracts/abis/CPKFactory.json
gnosis/eth/contracts/abis/CompatibilityFallbackHandler_V1_3_0.json
gnosis/eth/contracts/abis/CompatibilityFallbackHandler_V1_4_1.json
gnosis/eth/contracts/abis/DelegateConstructorProxy.json
gnosis/eth/contracts/abis/ERC1155.json
gnosis/eth/contracts/abis/ERC20.json
gnosis/eth/contracts/abis/ERC20TestToken.json
gnosis/eth/contracts/abis/ERC721.json
gnosis/eth/contracts/abis/GnosisSafe_V0_0_1.json
gnosis/eth/contracts/abis/GnosisSafe_V1_0_0.json
gnosis/eth/contracts/abis/GnosisSafe_V1_1_1.json
gnosis/eth/contracts/abis/GnosisSafe_V1_3_0.json
gnosis/eth/contracts/abis/MultiSend.json
gnosis/eth/contracts/abis/PayingProxy.json
gnosis/eth/contracts/abis/ProxyFactory_V1_0_0.json
gnosis/eth/contracts/abis/ProxyFactory_V1_1_1.json
gnosis/eth/contracts/abis/ProxyFactory_V1_3_0.json
gnosis/eth/contracts/abis/ProxyFactory_V1_4_1.json
gnosis/eth/contracts/abis/Proxy_V1_0_0.json
gnosis/eth/contracts/abis/Proxy_V1_1_1.json
gnosis/eth/contracts/abis/Proxy_V1_3_0.json
safe_yodaplus_py-6.0.1.dist-info/LICENSE
safe_yodaplus_py-6.0.1.dist-info/METADATA
safe_yodaplus_py-6.0.1.dist-info/WHEEL
safe_yodaplus_py-6.0.1.dist-info/top_level.txt
safe_yodaplus_py-6.0.1.dist-info/RECORD
